mechir/__init__.py
mechir/util.py
mechir/data/__init__.py
mechir/data/dataset.py
mechir/data/ir_dataset.py
mechir/data/loader/__init__.py
mechir/data/loader/base.py
mechir/data/loader/cat.py
mechir/data/loader/dot.py
mechir/data/loader/t5.py
mechir/modelling/__init__.py
mechir/modelling/cat.py
mechir/modelling/dot.py
mechir/modelling/patched.py
mechir/modelling/sae.py
mechir/modelling/steering.py
mechir/modelling/t5.py
mechir/modelling/architectures/__init__.py
mechir/modelling/architectures/base.py
mechir/modelling/architectures/distilbert.py
mechir/modelling/architectures/electra.py
mechir/modelling/hooked/__init__.py
mechir/modelling/hooked/components.py
mechir/modelling/hooked/config.py
mechir/modelling/hooked/conversion.py
mechir/modelling/hooked/linear.py
mechir/modelling/hooked/loading_from_pretrained.py
mechir/modelling/hooked/states.py
mechir/perturb/__init__.py
mechir/perturb/index.py
mechir/perturb/axiom/__init__.py
mechir/perturb/axiom/frequency.py
mechir/perturb/axiom/proximity.py
mechir/perturb/data/__init__.py
mechir/perturb/data/stopwords.txt
mechir/plotting/__init__.py
mechir/plotting/plotting_funcs.py
mechir/plotting/visualize_attn_patterns.py
mechir-0.0.4.dist-info/licenses/LICENSE
mechir-0.0.4.dist-info/METADATA
mechir-0.0.4.dist-info/WHEEL
mechir-0.0.4.dist-info/top_level.txt
mechir-0.0.4.dist-info/RECORD
