Metadata-Version: 2.4
Name: mechir
Version: 0.0.4
Summary: A package for mechanistic interpretability in Neural IR
Author: Anon A. Mous
Author-email: Andrew Parry <0andrewparry@gmail.com>, Catherine Chen <catherine_s_chen@brown.edu>
Maintainer-email: Andrew Parry <0andrewparry@gmail.com>
License:                                  Apache License
Project-URL: Repository, https://github.com/Parry-Parry/MechIR.git
Keywords: pytorch,transformers,ranking,information retrieval
Classifier: Programming Language :: Python
Classifier: License :: OSI Approved :: Apache Software License
Classifier: Operating System :: OS Independent
Classifier: Development Status :: 3 - Alpha
Classifier: Intended Audience :: Developers
Classifier: Intended Audience :: Science/Research
Classifier: Topic :: Scientific/Engineering :: Artificial Intelligence
Requires-Python: >=3.10
License-File: LICENSE
Requires-Dist: torch
Requires-Dist: transformers
Requires-Dist: transformer_lens
Requires-Dist: sae_lens
Requires-Dist: ir_datasets
Requires-Dist: streamlit
Requires-Dist: seaborn
Dynamic: author
Dynamic: license-file
Dynamic: requires-python
